utils_io/__init__.py
utils_io/filesession.py
utils_io/utils.py
utils_io-0.2.0.dist-info/METADATA
utils_io-0.2.0.dist-info/WHEEL
utils_io-0.2.0.dist-info/RECORD
