Metadata-Version: 2.3
Name: utils-io
Version: 0.2.0
Summary: utils-io
Author: overgodofchaos
Author-email: vezonzzzzzz@gmail.com
Requires-Python: >=3.11
Classifier: Programming Language :: Python :: 3
Classifier: Programming Language :: Python :: 3.11
Classifier: Programming Language :: Python :: 3.12
Classifier: Programming Language :: Python :: 3.13
